README.rst
setup.py
levelpy/__init__.py
levelpy/__meta__.py
levelpy/batch_context.py
levelpy/db_accessors.py
levelpy/iterviews.py
levelpy/leveldb.py
levelpy/leveldb_module_shims.py
levelpy/serializer.py
levelpy/sublevel.py
levelpy/view.py
levelpy.egg-info/PKG-INFO
levelpy.egg-info/SOURCES.txt
levelpy.egg-info/dependency_links.txt
levelpy.egg-info/top_level.txt
levelpy/async/__init__.py