Metadata-Version: 1.1
Name: levelpy
Version: 0.3.2
Summary: A pythonic interface to the LevelDB database.
Home-page: https://github.com/akubera/levelpy
Author: Andrew Kubera
Author-email: andrewkubera@gmail.com
License: MIT
Download-URL: https://github.com/akubera/levelpy/archive/v0.3.2.tar.gz
Platform: all
Classifier: Development Status :: 3 - Alpha
Classifier: License :: OSI Approved :: MIT License
Classifier: Operating System :: OS Independent
Classifier: Topic :: Database
Classifier: Programming Language :: Python
Classifier: Programming Language :: Python :: 3
Classifier: Natural Language :: English
